[
  {
    "id": 1,
    "url": "/assets/images/mercancias.webp",
    "text": "Servicio personalizado para movilizar mercancías",
    "subtext": "con información oportuna e indicadores de gestión"
  },
  {
    "id": 2,
    "url": "/assets/images/comercio.webp",
    "text": "Somos tu mejor aliado en logística internacional",
    "subtext": "todos los procedimientos aduaneros y de transporte"
  },
  {
    "id": 3,
    "url": "/assets/images/logistica.webp",
    "text": "Contamos con el mejor talento humano",
    "subtext": "para brindar un servicio de calidad y totalmente personalizado"
  }
]